osi_dump/__init__.py
osi_dump/__main__.py
osi_dump/cli.py
osi_dump/api/__init__.py
osi_dump/api/keystone.py
osi_dump/api/neutron.py
osi_dump/api/octavia.py
osi_dump/api/placement.py
osi_dump/batch_handler/__init__.py
osi_dump/batch_handler/external_port_batch_handler.py
osi_dump/batch_handler/flavor_batch_handler.py
osi_dump/batch_handler/floating_ip_batch_handler.py
osi_dump/batch_handler/hypervisor_batch_handler.py
osi_dump/batch_handler/image_batch_handler.py
osi_dump/batch_handler/instance_batch_handler.py
osi_dump/batch_handler/load_balancer_batch_handler.py
osi_dump/batch_handler/network_batch_handler.py
osi_dump/batch_handler/project_batch_handler.py
osi_dump/batch_handler/role_assignment_batch_handler.py
osi_dump/batch_handler/router_batch_handler.py
osi_dump/batch_handler/security_group_batch_handler.py
osi_dump/batch_handler/trunk_batch_handler.py
osi_dump/batch_handler/volume_batch_handler.py
osi_dump/exporter/__init__.py
osi_dump/exporter/external_port/__init__.py
osi_dump/exporter/external_port/excel_external_port_exporter.py
osi_dump/exporter/external_port/external_port_exporter.py
osi_dump/exporter/flavor/__init__.py
osi_dump/exporter/flavor/excel_flavor_exporter.py
osi_dump/exporter/flavor/flavor_exporter.py
osi_dump/exporter/floating_ip/__init__.py
osi_dump/exporter/floating_ip/excel_floating_ip_exporter.py
osi_dump/exporter/floating_ip/floating_ip_exporter.py
osi_dump/exporter/hypervisor/__init__.py
osi_dump/exporter/hypervisor/excel_hypervisor_exporter.py
osi_dump/exporter/hypervisor/hypervisor_exporter.py
osi_dump/exporter/image/__init__.py
osi_dump/exporter/image/excel_image_exporter.py
osi_dump/exporter/image/image_exporter.py
osi_dump/exporter/instance/__init__.py
osi_dump/exporter/instance/excel_instance_exporter.py
osi_dump/exporter/instance/instance_exporter.py
osi_dump/exporter/load_balancer/__init__.py
osi_dump/exporter/load_balancer/excel_load_balancer_exporter.py
osi_dump/exporter/load_balancer/load_balancer_exporter.py
osi_dump-0.3.1.2.dist-info/METADATA
osi_dump-0.3.1.2.dist-info/WHEEL
osi_dump-0.3.1.2.dist-info/entry_points.txt
osi_dump-0.3.1.2.dist-info/top_level.txt
osi_dump-0.3.1.2.dist-info/RECORD
