Metadata-Version: 2.4
Name: osi-dump
Version: 0.3.1.2
Summary: OpenStack information dump tool
Author: TVKain
License: Apache-2.0
Classifier: License :: OSI Approved :: Apache Software License
Requires-Python: >=3.10
Requires-Dist: typer
Requires-Dist: openstacksdk==3.3.0
Requires-Dist: pydantic
Requires-Dist: pandas
Requires-Dist: openpyxl
Requires-Dist: numpy
Provides-Extra: test
Requires-Dist: pytest; extra == "test"
